flet_permission_handler/__init__.py
flet_permission_handler/permission_handler.py
flet_permission_handler/types.py
flet_permission_handler-0.80.5.dist-info/licenses/LICENSE
flutter/flet_permission_handler/analysis_options.yaml
flutter/flet_permission_handler/pubspec.lock
flutter/flet_permission_handler/pubspec.yaml
flutter/flet_permission_handler/lib/flet_permission_handler.dart
flutter/flet_permission_handler/lib/src/extension.dart
flutter/flet_permission_handler/lib/src/permission_handler.dart
flutter/flet_permission_handler/lib/src/utils/permission_handler.dart
flet_permission_handler-0.80.5.dist-info/METADATA
flet_permission_handler-0.80.5.dist-info/WHEEL
flet_permission_handler-0.80.5.dist-info/top_level.txt
flet_permission_handler-0.80.5.dist-info/RECORD
